nonblock_server/__init__.py
nonblock_server/nonblock_server.py
nonblock_server-1.0.dist-info/LICENSE
nonblock_server-1.0.dist-info/METADATA
nonblock_server-1.0.dist-info/WHEEL
nonblock_server-1.0.dist-info/top_level.txt
nonblock_server-1.0.dist-info/RECORD
