Metadata-Version: 2.1
Name: nonblock-server
Version: 1.0
Summary: non-block http server for mpld3
Home-page: https://github.com/zjulujia/ssd.pytorch
Author: zjulujia
Author-email: zjulujia@gmail.com
License: UNKNOWN
Platform: UNKNOWN
Classifier: Programming Language :: Python :: 3
Classifier: License :: OSI Approved :: MIT License
Classifier: Operating System :: OS Independent
